{"1": {"recall": 93.10344827586206, "relret_len": 27.0, "rel_doc": 29.0, "prec": 3.237410071942446}, "2": {"recall": 88.0, "relret_len": 22.0, "rel_doc": 25.0, "prec": 2.8241335044929397}, "3": {"recall": 100.0, "relret_len": 9.0, "rel_doc": 9.0, "prec": 1.3493253373313343}, "4": {"recall": 100.0, "relret_len": 3.0, "rel_doc": 3.0, "prec": 0.2613240418118467}, "5": {"recall": 100.0, "relret_len": 5.0, "rel_doc": 5.0, "prec": 0.6963788300835655}, "6": {"recall": 100.0, "relret_len": 5.0, "rel_doc": 5.0, "prec": 0.5112474437627812}, "7": {"recall": 100.0, "relret_len": 6.0, "rel_doc": 6.0, "prec": 0.5725190839694656}, "8": {"recall": 100.0, "relret_len": 12.0, "rel_doc": 12.0, "prec": 0.990916597853014}, "9": {"recall": 100.0, "relret_len": 4.0, "rel_doc": 4.0, "prec": 0.39370078740157477}, "10": {"recall": 100.0, "relret_len": 9.0, "rel_doc": 9.0, "prec": 1.3761467889908259}, "11": {"recall": 100.0, "relret_len": 8.0, "rel_doc": 8.0, "prec": 0.81799591002045}, "12": {"recall": 100.0, "relret_len": 6.0, "rel_doc": 6.0, "prec": 0.5444646098003629}, "13": {"recall": 20.0, "relret_len": 1.0, "rel_doc": 5.0, "prec": 0.6802721088435374}, "14": {"recall": 100.0, "relret_len": 3.0, "rel_doc": 3.0, "prec": 0.5836575875486382}, "15": {"recall": 66.66666666666666, "relret_len": 2.0, "rel_doc": 3.0, "prec": 1.25}, "16": {"recall": 100.0, "relret_len": 4.0, "rel_doc": 4.0, "prec": 0.3988035892323031}, "17": {"recall": 100.0, "relret_len": 3.0, "rel_doc": 3.0, "prec": 0.2633889376646181}, "18": {"recall": 100.0, "relret_len": 4.0, "rel_doc": 4.0, "prec": 0.40609137055837563}, "19": {"recall": 80.0, "relret_len": 8.0, "rel_doc": 10.0, "prec": 0.7246376811594203}, "20": {"recall": 100.0, "relret_len": 10.0, "rel_doc": 10.0, "prec": 0.8503401360544218}, "21": {"recall": 100.0, "relret_len": 5.0, "rel_doc": 5.0, "prec": 0.6234413965087282}, "22": {"recall": 0.0, "relret_len": 0.0, "rel_doc": 2.0, "prec": 0.0}, "23": {"recall": 84.84848484848484, "relret_len": 28.0, "rel_doc": 33.0, "prec": 5.46875}, "24": {"recall": 100.0, "relret_len": 4.0, "rel_doc": 4.0, "prec": 0.6600660066006601}, "25": {"recall": 100.0, "relret_len": 10.0, "rel_doc": 10.0, "prec": 0.984251968503937}, "26": {"recall": 100.0, "relret_len": 7.0, "rel_doc": 7.0, "prec": 0.6081668114682884}, "27": {"recall": 100.0, "relret_len": 4.0, "rel_doc": 4.0, "prec": 0.46783625730994155}, "28": {"recall": 100.0, "relret_len": 3.0, "rel_doc": 3.0, "prec": 0.35335689045936397}, "29": {"recall": 100.0, "relret_len": 10.0, "rel_doc": 10.0, "prec": 0.8568980291345331}, "30": {"recall": 87.5, "relret_len": 7.0, "rel_doc": 8.0, "prec": 0.7329842931937173}, "31": {"recall": 100.0, "relret_len": 2.0, "rel_doc": 2.0, "prec": 0.15785319652722968}, "32": {"recall": 85.71428571428571, "relret_len": 6.0, "rel_doc": 7.0, "prec": 0.646551724137931}, "33": {"recall": 100.0, "relret_len": 4.0, "rel_doc": 4.0, "prec": 0.3597122302158274}, "34": {"recall": 100.0, "relret_len": 7.0, "rel_doc": 7.0, "prec": 0.8871989860583016}, "35": {"recall": 75.0, "relret_len": 3.0, "rel_doc": 4.0, "prec": 0.6818181818181818}, "36": {"recall": 100.0, "relret_len": 3.0, "rel_doc": 3.0, "prec": 0.3289473684210526}, "37": {"recall": 100.0, "relret_len": 10.0, "rel_doc": 10.0, "prec": 0.9881422924901186}, "38": {"recall": 100.0, "relret_len": 11.0, "rel_doc": 11.0, "prec": 1.877133105802048}, "39": {"recall": 78.57142857142857, "relret_len": 11.0, "rel_doc": 14.0, "prec": 1.5781922525107603}, "40": {"recall": 76.92307692307693, "relret_len": 10.0, "rel_doc": 13.0, "prec": 1.949317738791423}, "41": {"recall": 100.0, "relret_len": 4.0, "rel_doc": 4.0, "prec": 0.4728132387706856}, "42": {"recall": 100.0, "relret_len": 6.0, "rel_doc": 6.0, "prec": 0.5591798695246971}, "43": {"recall": 100.0, "relret_len": 7.0, "rel_doc": 7.0, "prec": 0.6641366223908919}, "44": {"recall": 0.0, "relret_len": 0.0, "rel_doc": 4.0, "prec": 0.0}, "45": {"recall": 100.0, "relret_len": 13.0, "rel_doc": 13.0, "prec": 1.310483870967742}, "46": {"recall": 100.0, "relret_len": 16.0, "rel_doc": 16.0, "prec": 1.4272970561998217}, "47": {"recall": 100.0, "relret_len": 15.0, "rel_doc": 15.0, "prec": 1.971090670170828}, "48": {"recall": 91.66666666666666, "relret_len": 11.0, "rel_doc": 12.0, "prec": 2.0257826887661143}, "49": {"recall": 100.0, "relret_len": 3.0, "rel_doc": 3.0, "prec": 0.2461033634126333}, "50": {"recall": 100.0, "relret_len": 7.0, "rel_doc": 7.0, "prec": 0.6616257088846881}, "51": {"recall": 100.0, "relret_len": 11.0, "rel_doc": 11.0, "prec": 0.9598603839441536}, "52": {"recall": 100.0, "relret_len": 5.0, "rel_doc": 5.0, "prec": 0.45871559633027525}, "53": {"recall": 100.0, "relret_len": 11.0, "rel_doc": 11.0, "prec": 1.004566210045662}, "54": {"recall": 100.0, "relret_len": 10.0, "rel_doc": 10.0, "prec": 1.1123470522803114}, "55": {"recall": 100.0, "relret_len": 11.0, "rel_doc": 11.0, "prec": 1.1627906976744187}, "56": {"recall": 100.0, "relret_len": 11.0, "rel_doc": 11.0, "prec": 1.2048192771084338}, "57": {"recall": 93.33333333333333, "relret_len": 14.0, "rel_doc": 15.0, "prec": 1.5334063526834611}, "58": {"recall": 100.0, "relret_len": 10.0, "rel_doc": 10.0, "prec": 0.8130081300813009}, "59": {"recall": 100.0, "relret_len": 5.0, "rel_doc": 5.0, "prec": 0.4686035613870665}, "60": {"recall": 100.0, "relret_len": 6.0, "rel_doc": 6.0, "prec": 0.5249343832020997}, "61": {"recall": 100.0, "relret_len": 6.0, "rel_doc": 6.0, "prec": 0.7220216606498195}, "62": {"recall": 100.0, "relret_len": 6.0, "rel_doc": 6.0, "prec": 0.5194805194805194}, "63": {"recall": 100.0, "relret_len": 4.0, "rel_doc": 4.0, "prec": 0.44004400440044}, "64": {"recall": 100.0, "relret_len": 3.0, "rel_doc": 3.0, "prec": 0.3125}, "65": {"recall": 93.75, "relret_len": 15.0, "rel_doc": 16.0, "prec": 1.3513513513513513}, "66": {"recall": 100.0, "relret_len": 6.0, "rel_doc": 6.0, "prec": 0.5415162454873645}, "67": {"recall": 100.0, "relret_len": 15.0, "rel_doc": 15.0, "prec": 1.3876040703052728}, "68": {"recall": 83.33333333333334, "relret_len": 5.0, "rel_doc": 6.0, "prec": 0.6684491978609626}, "69": {"recall": 100.0, "relret_len": 6.0, "rel_doc": 6.0, "prec": 0.6952491309385863}, "70": {"recall": 100.0, "relret_len": 11.0, "rel_doc": 11.0, "prec": 1.261467889908257}, "71": {"recall": 88.88888888888889, "relret_len": 8.0, "rel_doc": 9.0, "prec": 0.8888888888888888}, "72": {"recall": 94.44444444444444, "relret_len": 17.0, "rel_doc": 18.0, "prec": 1.6113744075829384}, "73": {"recall": 100.0, "relret_len": 21.0, "rel_doc": 21.0, "prec": 1.8867924528301887}, "74": {"recall": 100.0, "relret_len": 7.0, "rel_doc": 7.0, "prec": 0.7128309572301426}, "75": {"recall": 100.0, "relret_len": 6.0, "rel_doc": 6.0, "prec": 0.5076142131979695}, "76": {"recall": 100.0, "relret_len": 8.0, "rel_doc": 8.0, "prec": 0.6705783738474435}, "77": {"recall": 100.0, "relret_len": 7.0, "rel_doc": 7.0, "prec": 0.6334841628959276}, "78": {"recall": 100.0, "relret_len": 4.0, "rel_doc": 4.0, "prec": 1.593625498007968}, "79": {"recall": 100.0, "relret_len": 6.0, "rel_doc": 6.0, "prec": 0.5529953917050692}, "80": {"recall": 80.0, "relret_len": 4.0, "rel_doc": 5.0, "prec": 0.37914691943127965}, "81": {"recall": 100.0, "relret_len": 3.0, "rel_doc": 3.0, "prec": 0.46367851622874806}, "82": {"recall": 100.0, "relret_len": 6.0, "rel_doc": 6.0, "prec": 0.5093378607809848}, "83": {"recall": 100.0, "relret_len": 5.0, "rel_doc": 5.0, "prec": 0.4444444444444444}, "84": {"recall": 100.0, "relret_len": 12.0, "rel_doc": 12.0, "prec": 1.0300429184549356}, "85": {"recall": 100.0, "relret_len": 5.0, "rel_doc": 5.0, "prec": 0.4970178926441352}, "86": {"recall": 100.0, "relret_len": 3.0, "rel_doc": 3.0, "prec": 0.2964426877470355}, "87": {"recall": 100.0, "relret_len": 9.0, "rel_doc": 9.0, "prec": 0.779896013864818}, "88": {"recall": 100.0, "relret_len": 7.0, "rel_doc": 7.0, "prec": 1.3725490196078431}, "89": {"recall": 100.0, "relret_len": 7.0, "rel_doc": 7.0, "prec": 0.6704980842911877}, "90": {"recall": 100.0, "relret_len": 14.0, "rel_doc": 14.0, "prec": 1.6568047337278107}, "91": {"recall": 90.0, "relret_len": 9.0, "rel_doc": 10.0, "prec": 1.2802275960170697}, "92": {"recall": 100.0, "relret_len": 14.0, "rel_doc": 14.0, "prec": 1.3779527559055118}, "93": {"recall": 100.0, "relret_len": 2.0, "rel_doc": 2.0, "prec": 0.16556291390728478}, "94": {"recall": 100.0, "relret_len": 13.0, "rel_doc": 13.0, "prec": 1.5625}, "95": {"recall": 100.0, "relret_len": 3.0, "rel_doc": 3.0, "prec": 0.3973509933774834}, "96": {"recall": 100.0, "relret_len": 14.0, "rel_doc": 14.0, "prec": 1.3157894736842104}, "97": {"recall": 72.72727272727273, "relret_len": 8.0, "rel_doc": 11.0, "prec": 2.247191011235955}, "98": {"recall": 100.0, "relret_len": 6.0, "rel_doc": 6.0, "prec": 0.6230529595015576}, "99": {"recall": 80.0, "relret_len": 4.0, "rel_doc": 5.0, "prec": 0.5376344086021506}, "100": {"recall": 100.0, "relret_len": 10.0, "rel_doc": 10.0, "prec": 1.1709601873536302}, "101": {"recall": 100.0, "relret_len": 7.0, "rel_doc": 7.0, "prec": 0.7329842931937173}, "102": {"recall": 100.0, "relret_len": 5.0, "rel_doc": 5.0, "prec": 1.1086474501108647}, "103": {"recall": 66.66666666666666, "relret_len": 2.0, "rel_doc": 3.0, "prec": 0.7490636704119851}, "104": {"recall": 100.0, "relret_len": 6.0, "rel_doc": 6.0, "prec": 0.5655042412818096}, "105": {"recall": 100.0, "relret_len": 6.0, "rel_doc": 6.0, "prec": 0.8486562942008486}, "106": {"recall": 100.0, "relret_len": 6.0, "rel_doc": 6.0, "prec": 1.1673151750972763}, "107": {"recall": 100.0, "relret_len": 8.0, "rel_doc": 8.0, "prec": 0.8849557522123894}, "108": {"recall": 100.0, "relret_len": 8.0, "rel_doc": 8.0, "prec": 1.7738359201773837}, "109": {"recall": 100.0, "relret_len": 6.0, "rel_doc": 6.0, "prec": 1.125703564727955}, "110": {"recall": 100.0, "relret_len": 5.0, "rel_doc": 5.0, "prec": 0.5793742757821553}, "111": {"recall": 100.0, "relret_len": 8.0, "rel_doc": 8.0, "prec": 0.8879023307436182}, "112": {"recall": 100.0, "relret_len": 3.0, "rel_doc": 3.0, "prec": 0.2510460251046025}, "113": {"recall": 100.0, "relret_len": 5.0, "rel_doc": 5.0, "prec": 0.5107252298263534}, "114": {"recall": 100.0, "relret_len": 5.0, "rel_doc": 5.0, "prec": 0.4088307440719542}, "115": {"recall": 100.0, "relret_len": 5.0, "rel_doc": 5.0, "prec": 0.4108463434675432}, "116": {"recall": 100.0, "relret_len": 6.0, "rel_doc": 6.0, "prec": 0.8207934336525308}, "117": {"recall": 100.0, "relret_len": 3.0, "rel_doc": 3.0, "prec": 0.398406374501992}, "118": {"recall": 100.0, "relret_len": 4.0, "rel_doc": 4.0, "prec": 0.47393364928909953}, "119": {"recall": 100.0, "relret_len": 2.0, "rel_doc": 2.0, "prec": 0.17873100983020554}, "120": {"recall": 100.0, "relret_len": 10.0, "rel_doc": 10.0, "prec": 1.2468827930174564}, "121": {"recall": 100.0, "relret_len": 8.0, "rel_doc": 8.0, "prec": 1.257861635220126}, "122": {"recall": 100.0, "relret_len": 10.0, "rel_doc": 10.0, "prec": 0.9174311926605505}, "123": {"recall": 100.0, "relret_len": 3.0, "rel_doc": 3.0, "prec": 0.3021148036253776}, "124": {"recall": 100.0, "relret_len": 5.0, "rel_doc": 5.0, "prec": 0.3770739064856712}, "125": {"recall": 94.44444444444444, "relret_len": 17.0, "rel_doc": 18.0, "prec": 1.639344262295082}, "126": {"recall": 66.66666666666666, "relret_len": 6.0, "rel_doc": 9.0, "prec": 1.342281879194631}, "127": {"recall": 100.0, "relret_len": 6.0, "rel_doc": 6.0, "prec": 0.5612722170252572}, "128": {"recall": 100.0, "relret_len": 3.0, "rel_doc": 3.0, "prec": 0.36809815950920244}, "129": {"recall": 100.0, "relret_len": 8.0, "rel_doc": 8.0, "prec": 0.7359705611775529}, "130": {"recall": 100.0, "relret_len": 6.0, "rel_doc": 6.0, "prec": 0.7643312101910829}, "131": {"recall": 100.0, "relret_len": 9.0, "rel_doc": 9.0, "prec": 0.9316770186335404}, "132": {"recall": 100.0, "relret_len": 16.0, "rel_doc": 16.0, "prec": 3.1746031746031744}, "133": {"recall": 100.0, "relret_len": 8.0, "rel_doc": 8.0, "prec": 1.3675213675213675}, "134": {"recall": 100.0, "relret_len": 3.0, "rel_doc": 3.0, "prec": 0.2770083102493075}, "135": {"recall": 100.0, "relret_len": 9.0, "rel_doc": 9.0, "prec": 1.0638297872340425}, "136": {"recall": 100.0, "relret_len": 4.0, "rel_doc": 4.0, "prec": 0.4048582995951417}, "137": {"recall": 100.0, "relret_len": 5.0, "rel_doc": 5.0, "prec": 0.45454545454545453}, "138": {"recall": 100.0, "relret_len": 3.0, "rel_doc": 3.0, "prec": 0.31088082901554404}, "139": {"recall": 100.0, "relret_len": 5.0, "rel_doc": 5.0, "prec": 0.4488330341113106}, "140": {"recall": 100.0, "relret_len": 7.0, "rel_doc": 7.0, "prec": 0.9887005649717515}, "141": {"recall": 100.0, "relret_len": 7.0, "rel_doc": 7.0, "prec": 0.8177570093457943}, "142": {"recall": 100.0, "relret_len": 2.0, "rel_doc": 2.0, "prec": 0.2103049421661409}, "143": {"recall": 100.0, "relret_len": 3.0, "rel_doc": 3.0, "prec": 0.2859866539561487}, "144": {"recall": 100.0, "relret_len": 7.0, "rel_doc": 7.0, "prec": 0.697211155378486}, "145": {"recall": 100.0, "relret_len": 8.0, "rel_doc": 8.0, "prec": 0.7407407407407408}, "146": {"recall": 100.0, "relret_len": 3.0, "rel_doc": 3.0, "prec": 0.3157894736842105}, "147": {"recall": 90.9090909090909, "relret_len": 10.0, "rel_doc": 11.0, "prec": 1.488095238095238}, "148": {"recall": 100.0, "relret_len": 7.0, "rel_doc": 7.0, "prec": 0.8373205741626795}, "149": {"recall": 100.0, "relret_len": 12.0, "rel_doc": 12.0, "prec": 1.5444015444015444}, "150": {"recall": 100.0, "relret_len": 3.0, "rel_doc": 3.0, "prec": 0.3}, "151": {"recall": 100.0, "relret_len": 6.0, "rel_doc": 6.0, "prec": 0.5454545454545455}, "152": {"recall": 100.0, "relret_len": 7.0, "rel_doc": 7.0, "prec": 0.6129597197898424}, "153": {"recall": 87.5, "relret_len": 7.0, "rel_doc": 8.0, "prec": 1.2544802867383513}, "154": {"recall": 100.0, "relret_len": 3.0, "rel_doc": 3.0, "prec": 0.35294117647058826}, "155": {"recall": 71.42857142857143, "relret_len": 5.0, "rel_doc": 7.0, "prec": 1.1494252873563218}, "156": {"recall": 86.66666666666667, "relret_len": 13.0, "rel_doc": 15.0, "prec": 5.485232067510549}, "157": {"recall": 97.5, "relret_len": 39.0, "rel_doc": 40.0, "prec": 3.258145363408521}, "158": {"recall": 66.66666666666666, "relret_len": 6.0, "rel_doc": 9.0, "prec": 0.964630225080386}, "159": {"recall": 88.88888888888889, "relret_len": 8.0, "rel_doc": 9.0, "prec": 1.1904761904761905}, "160": {"recall": 100.0, "relret_len": 6.0, "rel_doc": 6.0, "prec": 0.5366726296958855}, "161": {"recall": 100.0, "relret_len": 7.0, "rel_doc": 7.0, "prec": 0.5747126436781609}, "162": {"recall": 100.0, "relret_len": 9.0, "rel_doc": 9.0, "prec": 0.8100810081008101}, "163": {"recall": 100.0, "relret_len": 4.0, "rel_doc": 4.0, "prec": 0.3404255319148936}, "164": {"recall": 100.0, "relret_len": 9.0, "rel_doc": 9.0, "prec": 1.048951048951049}, "165": {"recall": 100.0, "relret_len": 3.0, "rel_doc": 3.0, "prec": 0.3516998827667058}, "166": {"recall": 100.0, "relret_len": 9.0, "rel_doc": 9.0, "prec": 0.7887817703768624}, "167": {"recall": 100.0, "relret_len": 3.0, "rel_doc": 3.0, "prec": 0.27497708524289644}, "168": {"recall": 100.0, "relret_len": 3.0, "rel_doc": 3.0, "prec": 0.2533783783783784}, "169": {"recall": 100.0, "relret_len": 5.0, "rel_doc": 5.0, "prec": 0.398406374501992}, "170": {"recall": 100.0, "relret_len": 7.0, "rel_doc": 7.0, "prec": 0.7909604519774011}, "171": {"recall": 100.0, "relret_len": 4.0, "rel_doc": 4.0, "prec": 0.37174721189591076}, "172": {"recall": 100.0, "relret_len": 5.0, "rel_doc": 5.0, "prec": 0.5040322580645161}, "173": {"recall": 100.0, "relret_len": 3.0, "rel_doc": 3.0, "prec": 0.3282275711159737}, "174": {"recall": 100.0, "relret_len": 6.0, "rel_doc": 6.0, "prec": 0.6666666666666667}, "175": {"recall": 100.0, "relret_len": 6.0, "rel_doc": 6.0, "prec": 0.5988023952095809}, "176": {"recall": 100.0, "relret_len": 8.0, "rel_doc": 8.0, "prec": 0.7168458781362007}, "177": {"recall": 100.0, "relret_len": 6.0, "rel_doc": 6.0, "prec": 2.3166023166023164}, "178": {"recall": 100.0, "relret_len": 5.0, "rel_doc": 5.0, "prec": 0.998003992015968}, "179": {"recall": 100.0, "relret_len": 5.0, "rel_doc": 5.0, "prec": 0.39619651347068147}, "180": {"recall": 100.0, "relret_len": 8.0, "rel_doc": 8.0, "prec": 2.7777777777777777}, "181": {"recall": 100.0, "relret_len": 6.0, "rel_doc": 6.0, "prec": 0.5946481665014867}, "182": {"recall": 100.0, "relret_len": 3.0, "rel_doc": 3.0, "prec": 0.29041626331074544}, "183": {"recall": 92.85714285714286, "relret_len": 13.0, "rel_doc": 14.0, "prec": 2.564102564102564}, "184": {"recall": 100.0, "relret_len": 8.0, "rel_doc": 8.0, "prec": 1.7167381974248928}, "185": {"recall": 100.0, "relret_len": 10.0, "rel_doc": 10.0, "prec": 1.8450184501845017}, "186": {"recall": 100.0, "relret_len": 17.0, "rel_doc": 17.0, "prec": 1.471861471861472}, "187": {"recall": 85.71428571428571, "relret_len": 6.0, "rel_doc": 7.0, "prec": 0.5300353356890459}, "188": {"recall": 100.0, "relret_len": 12.0, "rel_doc": 12.0, "prec": 1.9077901430842605}, "189": {"recall": 90.0, "relret_len": 9.0, "rel_doc": 10.0, "prec": 0.9687836383207751}, "190": {"recall": 100.0, "relret_len": 6.0, "rel_doc": 6.0, "prec": 0.5791505791505791}, "191": {"recall": 100.0, "relret_len": 14.0, "rel_doc": 14.0, "prec": 3.2407407407407405}, "192": {"recall": 100.0, "relret_len": 5.0, "rel_doc": 5.0, "prec": 1.282051282051282}, "193": {"recall": 100.0, "relret_len": 10.0, "rel_doc": 10.0, "prec": 1.1185682326621924}, "194": {"recall": 100.0, "relret_len": 7.0, "rel_doc": 7.0, "prec": 0.7567567567567568}, "195": {"recall": 100.0, "relret_len": 4.0, "rel_doc": 4.0, "prec": 0.3755868544600939}, "196": {"recall": 92.3076923076923, "relret_len": 12.0, "rel_doc": 13.0, "prec": 0.990916597853014}, "197": {"recall": 100.0, "relret_len": 4.0, "rel_doc": 4.0, "prec": 0.46565774155995343}, "198": {"recall": 100.0, "relret_len": 5.0, "rel_doc": 5.0, "prec": 0.4835589941972921}, "199": {"recall": 88.88888888888889, "relret_len": 8.0, "rel_doc": 9.0, "prec": 1.103448275862069}, "200": {"recall": 100.0, "relret_len": 4.0, "rel_doc": 4.0, "prec": 0.4405286343612335}, "201": {"recall": 100.0, "relret_len": 17.0, "rel_doc": 17.0, "prec": 2.4285714285714284}, "202": {"recall": 100.0, "relret_len": 15.0, "rel_doc": 15.0, "prec": 1.3440860215053763}, "203": {"recall": 93.33333333333333, "relret_len": 14.0, "rel_doc": 15.0, "prec": 1.2681159420289856}, "204": {"recall": 93.33333333333333, "relret_len": 14.0, "rel_doc": 15.0, "prec": 1.4271151885830784}, "205": {"recall": 100.0, "relret_len": 3.0, "rel_doc": 3.0, "prec": 0.30181086519114686}, "206": {"recall": 100.0, "relret_len": 4.0, "rel_doc": 4.0, "prec": 0.4008016032064128}, "207": {"recall": 100.0, "relret_len": 6.0, "rel_doc": 6.0, "prec": 0.6217616580310881}, "208": {"recall": 100.0, "relret_len": 7.0, "rel_doc": 7.0, "prec": 0.6535947712418301}, "209": {"recall": 100.0, "relret_len": 13.0, "rel_doc": 13.0, "prec": 1.279527559055118}, "210": {"recall": 100.0, "relret_len": 7.0, "rel_doc": 7.0, "prec": 0.6717850287907869}, "211": {"recall": 100.0, "relret_len": 12.0, "rel_doc": 12.0, "prec": 1.366742596810934}, "212": {"recall": 100.0, "relret_len": 15.0, "rel_doc": 15.0, "prec": 1.7241379310344827}, "213": {"recall": 100.0, "relret_len": 12.0, "rel_doc": 12.0, "prec": 1.2958963282937366}, "214": {"recall": 100.0, "relret_len": 5.0, "rel_doc": 5.0, "prec": 0.562429696287964}, "215": {"recall": 100.0, "relret_len": 3.0, "rel_doc": 3.0, "prec": 0.29296875}, "216": {"recall": 100.0, "relret_len": 2.0, "rel_doc": 2.0, "prec": 0.1834862385321101}, "217": {"recall": 100.0, "relret_len": 16.0, "rel_doc": 16.0, "prec": 1.4828544949026876}, "218": {"recall": 100.0, "relret_len": 16.0, "rel_doc": 16.0, "prec": 2.6936026936026933}, "219": {"recall": 100.0, "relret_len": 19.0, "rel_doc": 19.0, "prec": 1.6101694915254237}, "220": {"recall": 100.0, "relret_len": 20.0, "rel_doc": 20.0, "prec": 1.6433853738701727}, "221": {"recall": 100.0, "relret_len": 19.0, "rel_doc": 19.0, "prec": 1.5510204081632653}, "222": {"recall": 100.0, "relret_len": 10.0, "rel_doc": 10.0, "prec": 1.557632398753894}, "223": {"recall": 100.0, "relret_len": 5.0, "rel_doc": 5.0, "prec": 0.9345794392523363}, "224": {"recall": 100.0, "relret_len": 9.0, "rel_doc": 9.0, "prec": 0.8159564823209429}, "225": {"recall": 88.0, "relret_len": 22.0, "rel_doc": 25.0, "prec": 2.099236641221374}}